PandasCookbookDaiZhushiYuanma/README.md
PandasCookbookDaiZhushiYuanma/__init__.py
PandasCookbookDaiZhushiYuanma/__main__.py
PandasCookbookDaiZhushiYuanma/file.epub
PandasCookbookDaiZhushiYuanma/index.html
PandasCookbookDaiZhushiYuanma/css/__init__.py
PandasCookbookDaiZhushiYuanma/css/annotations.css
PandasCookbookDaiZhushiYuanma/css/main.css
PandasCookbookDaiZhushiYuanma/css/normalize.css
PandasCookbookDaiZhushiYuanma/css/popup.css
PandasCookbookDaiZhushiYuanma/font/__init__.py
PandasCookbookDaiZhushiYuanma/font/fontello.eot
PandasCookbookDaiZhushiYuanma/font/fontello.svg
PandasCookbookDaiZhushiYuanma/font/fontello.ttf
PandasCookbookDaiZhushiYuanma/font/fontello.woff
PandasCookbookDaiZhushiYuanma/img/__init__.py
PandasCookbookDaiZhushiYuanma/img/annotator-glyph-sprite.png
PandasCookbookDaiZhushiYuanma/img/annotator-icon-sprite.png
PandasCookbookDaiZhushiYuanma/img/apple-touch-icon.png
PandasCookbookDaiZhushiYuanma/img/cancelfullscreen.png
PandasCookbookDaiZhushiYuanma/img/close.png
PandasCookbookDaiZhushiYuanma/img/fullscreen.png
PandasCookbookDaiZhushiYuanma/img/loader.gif
PandasCookbookDaiZhushiYuanma/img/menu-icon.png
PandasCookbookDaiZhushiYuanma/img/save.png
PandasCookbookDaiZhushiYuanma/img/saved.png
PandasCookbookDaiZhushiYuanma/img/settings-s.png
PandasCookbookDaiZhushiYuanma/img/settings.png
PandasCookbookDaiZhushiYuanma/img/star.png
PandasCookbookDaiZhushiYuanma/js/__init__.py
PandasCookbookDaiZhushiYuanma/js/epub.js
PandasCookbookDaiZhushiYuanma/js/epub.min.js
PandasCookbookDaiZhushiYuanma/js/epub.min.map
PandasCookbookDaiZhushiYuanma/js/hooks.min.js
PandasCookbookDaiZhushiYuanma/js/hooks.min.map
PandasCookbookDaiZhushiYuanma/js/reader.js
PandasCookbookDaiZhushiYuanma/js/reader.js.map
PandasCookbookDaiZhushiYuanma/js/reader.min.js
PandasCookbookDaiZhushiYuanma/js/reader.min.map
PandasCookbookDaiZhushiYuanma/js/hooks/__init__.py
PandasCookbookDaiZhushiYuanma/js/hooks/extensions/__init__.py
PandasCookbookDaiZhushiYuanma/js/hooks/extensions/highlight.js
pandas_cookbook_dai_zhushi_yuanma-2024.3.3.0.dist-info/METADATA
pandas_cookbook_dai_zhushi_yuanma-2024.3.3.0.dist-info/WHEEL
pandas_cookbook_dai_zhushi_yuanma-2024.3.3.0.dist-info/entry_points.txt
pandas_cookbook_dai_zhushi_yuanma-2024.3.3.0.dist-info/top_level.txt
pandas_cookbook_dai_zhushi_yuanma-2024.3.3.0.dist-info/RECORD
